{
  "id": 10738,
  "slug": "10738",
  "title": "Find company LinkedIn URLs using Apify - Google Sheets integration",
  "description": "## Find Company linkedin Urls directly in Google sheets\n\nThis n8n template shows how to populate a Google Spreadsheet with LinkedIn company URLs automatically using the [Apify LinkedIn Company URL Finder actor](https://apify.com/anchor/linkedin-company-url-finder) from [Anchor](https://apify.com/anchor). It will create a new sheet with the matched LinkedIn URLs.\n\n![workflow tempalte screenshot overview](https://i.postimg.cc/sXWsfgL8/Screenshot-2025-11-11-at-21-49-31.png)\n\nYou can use it to speed up lead research, keep CRM records consistent, or prep outreach lists — all directly inside n8n.\n\n### Who is this for\n- Sales Teams: Map accounts to their official LinkedIn pages fast.\n- Recruiters: Locate company pages before sourcing.\n- Growth Marketers: Clean and enrich account lists at scale.\n- Researchers: Track competitors and market segments.\n- CRM Builders: Normalize company records with an authoritative URL.\n- Lead-Gen Agencies: Deliver verified company URLs at volume.\n\n### How it works\n- Write a list of company names in Google Sheets (one per row)\n- The Apify node resolves each name to its LinkedIn company page\n- The results are then stored in a new Google Sheet\n\n### How to use\n\nIn Google Sheets:\n- Create a Google Sheet, rename the sheet companies, and add all the company names you want to resolve (one per row)\n\n\nIn this Workflow:\n- Open “Set google sheet URL & original sheet name” and replace the example Google Sheet URL, and the name of the sheet where your company names are.\n\n\nIn the n8n credentials:\n- Connect your Google Sheets account with read and write privileges.\n- Connect your Apify account.\n\n\nIn Apify:\n- Sign up for this [Apify Actor](https://apify.com/anchor/linkedin-company-url-finder)￼ \n\n### Requirements\n- Apify account with access to LinkedIn Company URL Finder.\n- A list of company names to process.\n\n### Need Help?\nOpen an issue directly on Apify! Avg answer in less than 24h\n\n\nHappy URL Finding!",
  "featuredImage": "/data/workflows/10738/10738.webp",
  "author": {
    "id": 101,
    "slug": "anchor",
    "name": "Anchor",
    "avatar": ""
  },
  "categories": [
    "Lead Generation"
  ],
  "complexityLevel": "intermediate",
  "price": 0,
  "visitors": 61,
  "downloads": 6,
  "createdAt": "2025-11-11T20:51:08.309Z",
  "updatedAt": "2026-01-16T09:06:06.132Z",
  "publishedAt": "2025-11-11T20:51:08.309Z",
  "nodes": 13,
  "version": "1.0.0",
  "sourceUrl": "https://n8n.io/workflows/10738"
}