{
  "id": 903,
  "slug": "903",
  "title": "Discover professional emails with uProc and send via Telegram",
  "description": "![image.png](fileId:1033)\n\nThis **n8n workflow template** uses **uProc's \"Get Email by Domain, Firstname and Lastname\" tool** to discover a professional email address, and then sends that email to a **Telegram channel**.\n\n&gt; ⚠️ *Note: You must set up your **uProc credentials (Email + API Key)** from the [**Integration settings**](https://app.uproc.io/#/settings/integration) before running this workflow.*\n\n---\n\n### 🚀 **What It Does**\n\n- Uses user-provided data: **first name**, **last name**, and **company domain**\n- Calls **uProc** to discover the most likely email address for that person\n- Sends the discovered email and confidence level to a **Telegram group**\n\n---\n\n### 🛠️ **Step-by-Step Setup**\n\n1. **Add uProc Credentials**  \n   Go to the [uProc integration page](https://app.uproc.io/#/settings/integration) and copy your **email and API key**.  \n   Add them as credentials in your n8n instance.\n\n2. **Set Tool Parameters**  \n   - Use the **Set node** to define:\n     - `firstname`: First name of the person\n     - `lastname`: Last name of the person\n     - `domain`: Their company domain\n\n3. **Replace the Set Node (Optional)**  \n   You can dynamically fetch the `firstname`, `lastname`, and `domain` from other sources like:\n   - **Google Sheets**\n   - **MySQL or Postgres**\n   - **Webhook or Form submissions**\n\n4. **Run the Workflow**  \n   Trigger the flow manually or integrate it with a larger automation.\n\n---\n\n### 🔍 **uProc Parameters Explained**\n\n- **domain**: The company domain (e.g., `uproc.io`)\n- **firstname**: First name of the person\n- **lastname** (in parameter: `language`): Last name of the person\n- **mode**:\n  - `verify`: Verifies email in real-time with mail server\n  - `guess`: Guesses based on company format (e.g., `firstname.lastname@domain.com`)\n\n---\n\n### 📦 **uProc Response Fields**\n\n- `email`: Discovered email address\n- `confidence`: Indicates if the result is verified or risky (e.g., catch-all)\n- `score`: Reliability score from **0** (unreliable) to **99** (highly reliable)\n\n---\n\n### 📬 **Notification via Telegram**\n\nAfter discovering the email, the result is sent to a specified **Telegram channel** with this format:\n\n```text\nUser Miquel Colomer has next email on uproc.io: contact@uproc.io (verified - 99)\n```\n\n\nClicking the email allows you to send a message directly to the recipient.\n\n---\n\n### 🔐 **Credentials Used**\n\n- **uProc API** – For discovering email addresses\n- **Telegram API** – To send messages to a specific group/channel\n\n---\n\n### ✨ **Customization Tips**\n\n- **Loop over a list of people**: Replace the set node with a data source that contains multiple people.\n- **Filter by score or confidence** before sending.\n- **Add additional outputs**: You can send the data via Email, Slack, or save it to a database.\n- **Trigger automatically**: Combine with a webhook or time-based trigger for automation.\n\n---\n\n### ❓Questions?\n\nTemplate created by [**Miquel Colomer**](https://www.linkedin.com/in/miquelcolomersalas/) and [**n8nhackers.com**](https://n8nhackers.com). \n \nNeed help customizing or deploying? [**Contact us**](mailto:contact@n8nhackers.com) for consulting and support.",
  "featuredImage": "/data/workflows/903/903.webp",
  "author": {
    "id": 101,
    "slug": "mcolomer",
    "name": "Miquel Colomer",
    "avatar": ""
  },
  "categories": [
    "Lead Generation"
  ],
  "complexityLevel": "beginner",
  "price": 0,
  "visitors": 134,
  "downloads": 13,
  "createdAt": "2021-01-24T11:25:06.962Z",
  "updatedAt": "2026-01-16T08:20:21.438Z",
  "publishedAt": "2021-01-24T11:25:06.962Z",
  "nodes": 4,
  "version": "1.0.0",
  "sourceUrl": "https://n8n.io/workflows/903",
  "disclaimer": "This workflow is provided as-is. Please review and test before using in production.",
  "overview": {
    "title": "Discover professional emails with uProc and send via Telegram",
    "workflowName": "Discover professional emails with uProc and send via Telegram",
    "description": "![image.png](fileId:1033)\n\nThis **n8n workflow template** uses **uProc's \"Get Email by Domain, Firstname and Lastname\" tool** to discover a professional email address, and then sends that email to a **Telegram channel**.\n\n&gt; ⚠️ *Note: You must set up your **uProc credentials (Email + API Key)** from the [**Integration settings**](https://app.uproc.io/#/settings/integration) before running this workflow.*\n\n---\n\n### 🚀 **What It Does**\n\n- Uses user-provided data: **first name**, **last name**, and **company domain**\n- Calls **uProc** to discover the most likely email address for that person\n- Sends the discovered email and confidence level to a **Telegram group**\n\n---\n\n### 🛠️ **Step-by-Step Setup**\n\n1. **Add uProc Credentials**  \n   Go to the [uProc integration page](https://app.uproc.io/#/settings/integration) and copy your **email and API key**.  \n   Add them as credentials in your n8n instance.\n\n2. **Set Tool Parameters**  \n   - Use the **Set node** to define:\n     - `firstname`: First name of the person\n     - `lastname`: Last name of the person\n     - `domain`: Their company domain\n\n3. **Replace the Set Node (Optional)**  \n   You can dynamically fetch the `firstname`, `lastname`, and `domain` from other sources like:\n   - **Google Sheets**\n   - **MySQL or Postgres**\n   - **Webhook or Form submissions**\n\n4. **Run the Workflow**  \n   Trigger the flow manually or integrate it with a larger automation.\n\n---\n\n### 🔍 **uProc Parameters Explained**\n\n- **domain**: The company domain (e.g., `uproc.io`)\n- **firstname**: First name of the person\n- **lastname** (in parameter: `language`): Last name of the person\n- **mode**:\n  - `verify`: Verifies email in real-time with mail server\n  - `guess`: Guesses based on company format (e.g., `firstname.lastname@domain.com`)\n\n---\n\n### 📦 **uProc Response Fields**\n\n- `email`: Discovered email address\n- `confidence`: Indicates if the result is verified or risky (e.g., catch-all)\n- `score`: Reliability score from **0** (unreliable) to **99** (highly reliable)\n\n---\n\n### 📬 **Notification via Telegram**\n\nAfter discovering the email, the result is sent to a specified **Telegram channel** with this format:\n\n```text\nUser Miquel Colomer has next email on uproc.io: contact@uproc.io (verified - 99)\n```\n\n\nClicking the email allows you to send a message directly to the recipient.\n\n---\n\n### 🔐 **Credentials Used**\n\n- **uProc API** – For discovering email addresses\n- **Telegram API** – To send messages to a specific group/channel\n\n---\n\n### ✨ **Customization Tips**\n\n- **Loop over a list of people**: Replace the set node with a data source that contains multiple people.\n- **Filter by score or confidence** before sending.\n- **Add additional outputs**: You can send the data via Email, Slack, or save it to a database.\n- **Trigger automatically**: Combine with a webhook or time-based trigger for automation.\n\n---\n\n### ❓Questions?\n\nTemplate created by [**Miquel Colomer**](https://www.linkedin.com/in/miquelcolomersalas/) and [**n8nhackers.com**](https://n8nhackers.com). \n \nNeed help customizing or deploying? [**Contact us**](mailto:contact@n8nhackers.com) for consulting and support.",
    "features": [],
    "useCases": []
  },
  "logicalBlocks": [],
  "nodeDetails": [
    {
      "name": "On clicking 'execute'",
      "type": "n8n-nodes-base.manualTrigger",
      "role": "manualTrigger",
      "configDescription": "Version 1"
    },
    {
      "name": "Telegram",
      "type": "n8n-nodes-base.telegram",
      "role": "telegram",
      "configDescription": "Version 1"
    },
    {
      "name": "Get Email",
      "type": "n8n-nodes-base.uproc",
      "role": "uproc",
      "configDescription": "Version 1"
    },
    {
      "name": "Set Tool Parameters",
      "type": "n8n-nodes-base.set",
      "role": "set",
      "configDescription": "Version 1"
    }
  ]
}