{
  "id": 4715,
  "slug": "4715",
  "title": "Daily validated business ideas using n8n and Upwork",
  "description": "**How it works**\n- Runs at set times to fetch new Upwork job listings.\n- Checks each job’s total or hourly budget and keeps only higher-budget ones.\n- Extracts the job description for those selected jobs.\n- Uses AI to identify the core business idea from each description.\n- Records the idea and job details into a Google Sheet.\n- Can also be triggered manually to process a single job description.\n\n**Set up steps**\n\n- **Required:** Upwork API key, AI service key, and a Google Sheet.\n- **Import:** Bring the JSON into n8n.\n- **Configure:** Enter your API keys and connect to your Google Sheet.\n- **Time:** About 25–35 minutes to complete all steps.\n- **Notes:** Detailed setup instructions are added as sticky notes inside the workflow.",
  "featuredImage": "/data/workflows/4715/4715.webp",
  "author": {
    "id": 101,
    "slug": "architjn",
    "name": "Archit Jain",
    "avatar": ""
  },
  "categories": [
    "Market Research",
    "AI Summarization"
  ],
  "complexityLevel": "advanced",
  "price": 0,
  "visitors": 755,
  "downloads": 75,
  "createdAt": "2025-06-06T05:41:25.897Z",
  "updatedAt": "2026-01-16T08:35:47.868Z",
  "publishedAt": "2025-06-06T05:41:25.897Z",
  "nodes": 20,
  "version": "1.0.0",
  "sourceUrl": "https://n8n.io/workflows/4715"
}