{
  "id": 871,
  "slug": "871",
  "title": "N8N español - Tratamiento de textos",
  "description": "![workflow-screenshot](fileId:367)\n\nEste workflow es para trabajar con tratamiento de texto usando n8n y poder iniciarte en como funciona.\n\n**How To, Paso a Paso:** [https://comunidad-n8n.com/tratamiento-de-textos/](https://comunidad-n8n.com/tratamiento-de-textos/)\n\n**Comunidad de telegram:** [https://t.me/comunidadn8n](https://t.me/comunidadn8n)",
  "featuredImage": "/data/workflows/871/871.webp",
  "author": {
    "id": 101,
    "slug": "tuxed",
    "name": "The { AI } rtist",
    "avatar": ""
  },
  "categories": [
    "Miscellaneous"
  ],
  "complexityLevel": "intermediate",
  "price": 0,
  "visitors": 4983,
  "downloads": 498,
  "createdAt": "2021-01-02T12:46:16.279Z",
  "updatedAt": "2026-01-16T08:20:16.435Z",
  "publishedAt": "2021-01-02T12:46:16.279Z",
  "nodes": 7,
  "version": "1.0.0",
  "sourceUrl": "https://n8n.io/workflows/871"
}