{
  "id": 6301,
  "slug": "6301",
  "title": "Extract actionable security insights from HackerOne reports with Google Gemini",
  "description": "A streamlined AI-powered tool that extracts actionable technical insights from HackerOne security reports for advanced bug bounty hunters.\n\n## How It Works\nSend any HackerOne report URL (e.g., https://hackerone.com/reports/123456) to the chat interface. The AI agent will:\n\n1. Fetch the report JSON automatically\n2. Analyze for unique techniques, payloads, and root causes\n3. Extract reusable insights in a structured format\nSummarize with practical pentesting value\n\n## Setup Requirements\n\n1. Google Gemini API credentials configured\n2. Chat interface deployed and accessible\n3. HackerOne report URLs\n\n## Output Format\n\n1. Summary: One-liner impact statement\n2. Techniques: Payloads, code snippets, exploitation steps\n3. Pro Tips: Reusable insights for future hunts\n\nPerfect for rapid triage and building your personal exploit knowledge base.",
  "featuredImage": "/data/workflows/6301/6301.webp",
  "author": {
    "id": 101,
    "slug": "ethicxlhuman",
    "name": "Kunsh",
    "avatar": ""
  },
  "categories": [
    "SecOps",
    "AI Summarization"
  ],
  "complexityLevel": "intermediate",
  "price": 0,
  "visitors": 605,
  "downloads": 60,
  "createdAt": "2025-07-23T05:00:52.397Z",
  "updatedAt": "2026-01-16T08:44:19.204Z",
  "publishedAt": "2025-07-23T05:00:52.397Z",
  "nodes": 9,
  "version": "1.0.0",
  "sourceUrl": "https://n8n.io/workflows/6301"
}