{
  "id": 1822,
  "slug": "1822",
  "title": "Two way sync Pipedrive and MySQL",
  "description": "This workflow automates a two way sync of customer data between Pipedrive and MySQL. It will create new records in one source if it only exists in the other. Where matching records have different data for name, phone number or email address, it will sync the most recently updated version.",
  "featuredImage": "/data/workflows/1822/1822.webp",
  "author": {
    "id": 101,
    "slug": "n8n-team",
    "name": "n8n Team",
    "avatar": ""
  },
  "categories": [
    "CRM"
  ],
  "complexityLevel": "intermediate",
  "price": 0,
  "visitors": 14338,
  "downloads": 1433,
  "createdAt": "2022-11-03T14:20:34.511Z",
  "updatedAt": "2026-01-16T08:22:03.768Z",
  "publishedAt": "2022-11-03T14:20:34.511Z",
  "nodes": 14,
  "version": "1.0.0",
  "sourceUrl": "https://n8n.io/workflows/1822"
}